chilicloud/__init__.py
chilicloud/chilicloud.py
chilicloud-0.0.1.dist-info/LICENSE
chilicloud-0.0.1.dist-info/METADATA
chilicloud-0.0.1.dist-info/WHEEL
chilicloud-0.0.1.dist-info/top_level.txt
chilicloud-0.0.1.dist-info/RECORD
