Metadata-Version: 2.1
Name: chilicloud
Version: 0.0.1
Summary: A simple api wrapper for Chilicloud.
Home-page: UNKNOWN
Author: Ha1fdan
Author-email: <ha1fdan@ha1fdan.xyz>
License: UNKNOWN
Keywords: python,chilicloud,chiliprotect,api,api-wrapper
Platform: UNKNOWN
Classifier: Development Status :: 1 - Planning
Classifier: Intended Audience :: Developers
Classifier: Programming Language :: Python :: 3
Classifier: Operating System :: Unix
Classifier: Operating System :: MacOS :: MacOS X
Classifier: Operating System :: Microsoft :: Windows
License-File: LICENSE
Requires-Dist: dotenv-python
Requires-Dist: requests
